setup.py
django_jsonresponse.egg-info/PKG-INFO
django_jsonresponse.egg-info/SOURCES.txt
django_jsonresponse.egg-info/dependency_links.txt
django_jsonresponse.egg-info/top_level.txt
jsonresponse/__init__.py
tests/__init__.py