Metadata-Version: 1.1
Name: django-jsonresponse
Version: 0.8.1
Summary: Simple wrap django views to render json 
Home-page: http://github.com/jjay/django-jsonresponse
Author: Yasha Borevich
Author-email: j.borevich@gmail.com
License: UNKNOWN
Platform: any
Classifier: Development Status :: 4 - Beta
Classifier: Framework :: Django
Classifier: Intended Audience :: Developers
Classifier: License :: OSI Approved :: BSD License
Classifier: Operating System :: OS Independent
Classifier: Programming Language :: Python
Classifier: Topic :: Internet :: WWW/HTTP
